swh/__init__.py
swh/loader/__init__.py
swh/loader/tar/__init__.py
swh/loader/tar/_version.py
swh/loader/tar/build.py
swh/loader/tar/loader.py
swh/loader/tar/py.typed
swh/loader/tar/tasks.py
swh/loader/tar/utils.py
swh/loader/tar/tests/__init__.py
swh/loader/tar/tests/conftest.py
swh/loader/tar/tests/test_build.py
swh/loader/tar/tests/test_loader.py
swh/loader/tar/tests/test_tasks.py
swh/loader/tar/tests/test_utils.py
swh/loader/tar/tests/resources/sample-folder.tgz
swh.loader.tar-0.0.41.dist-info/AUTHORS
swh.loader.tar-0.0.41.dist-info/LICENSE
swh.loader.tar-0.0.41.dist-info/METADATA
swh.loader.tar-0.0.41.dist-info/WHEEL
swh.loader.tar-0.0.41.dist-info/top_level.txt
swh.loader.tar-0.0.41.dist-info/RECORD
