Metadata-Version: 2.1
Name: swh.loader.tar
Version: 0.0.41
Summary: Software Heritage Tarball Loader
Home-page: https://forge.softwareheritage.org/diffusion/DLDTAR
Author: Software Heritage developers
Author-email: swh-devel@inria.fr
License: UNKNOWN
Project-URL: Bug Reports, https://forge.softwareheritage.org/maniphest
Project-URL: Funding, https://www.softwareheritage.org/donate
Project-URL: Source, https://forge.softwareheritage.org/source/swh-loader-tar
Platform: UNKNOWN
Classifier: Programming Language :: Python :: 3
Classifier: Intended Audience :: Developers
Classifier: License :: OSI Approved :: GNU General Public License v3 (GPLv3)
Classifier: Operating System :: OS Independent
Classifier: Development Status :: 5 - Production/Stable
Requires-Dist: arrow
Requires-Dist: vcversioner
Requires-Dist: requests
Requires-Dist: click
Requires-Dist: python-dateutil
Requires-Dist: swh.core (>=0.0.46)
Requires-Dist: swh.model (>=0.0.27)
Requires-Dist: swh.scheduler (>=0.0.39)
Requires-Dist: swh.storage (>=0.0.83)
Requires-Dist: swh.loader.core (>=0.0.35)
Requires-Dist: swh.loader.dir (>=0.0.33)
Provides-Extra: testing
Requires-Dist: pytest (<4) ; extra == 'testing'
Requires-Dist: swh-scheduler[testing] ; extra == 'testing'
Requires-Dist: requests-mock ; extra == 'testing'
